[{"name":"PunishDisplay"},{"name":"ReplayDnD"},{"name":"ScoreTracker"},{"name":"shady-loader"},{"name":"ReplayInputView"},{"name":"SaveRep"},{"name":"th123intl"},{"name":"Blacklist"},{"name":"ChainCFix"},{"name":"IPv6MapSokuMod"},{"name":"MemoryPatch"},{"name":"EasyDecks"},{"name":"FixMeiling236"},{"name":"GetIP"},{"name":"LabTool"},{"name":"NetBattleCounter"},{"name":"PracticeEx"},{"name":"SokuLobbiesMod"},{"name":"palette-picker"},{"name":"Autopunch"},{"name":"BGMChanger"},{"name":"CharactersInForeground"},{"name":"Giuroll"},{"name":"NetProfileView"},{"name":"NetBellChanger"},{"name":"InGameHostlist"},{"name":"DPadFix"},{"name":"DiscordIntegration"}]