{"version":"1.1.0.0","main":"d3d9.dll","notes":"* 此项内容为默认mod配置的更新（ModLoaderSettings-default.json 和 SWRSToys-default.ini），点击更新后不会立即更改mod配置，再点击“【 恢复默认 SWRStoys 配置 】.bat”即可更新mod配置\n* 目前关闭了 DesyncProtector 和 giuroll_desync_detector 不同步侦测mod\n### [跳转链接——如何开关配置 mod](https://wiki.514.live/mods/WhatsMod.html)","notesI18n":[],"configFiles":["123.ini"],"downloadLinks":[{"type":"gitee","url":"https://gitee.com/soku-cn/SokuModLoader/releases/download/v1.1.0.0/SokuModLoader_1.1.0.0.zip"},{"type":"github","url":"https://github.com/soku-cn/SokuModLoader/releases/download/v1.1.0.0/SokuModLoader_1.1.0.0.zip"}]}